{
  "local_page": false,
  "listing_group": "main",
  "pub_type": "conference",
  "pub_year": 2021,
  "pub_date": "2021-01-04",
  "primary_link": "publisher",
  "title": "egg: Fast and Extensible Equality Saturation",
  "authors": [
    {
      "name": "Max Willsey"
    },
    {
      "name": "Chandrakana Nandi"
    },
    {
      "name": "Yisu Remy Wang",
      "ref": "Remy Wang"
    },
    {
      "name": "Oliver Flatt"
    },
    {
      "name": "Zachary Tatlock"
    },
    {
      "name": "Pavel Panchekha"
    }
  ],
  "venue": "Principles of Programming Languages",
  "venue_short": "POPL",
  "badges": [
    "★ Distinguished Paper"
  ],
  "links": {
    "publisher": "https://dl.acm.org/doi/10.1145/3434304"
  }
}
